README.rst
setup.py
pull_scp/__init__.py
pull_scp/__main__.py
pull_scp/client.py
pull_scp/config.py
pull_scp/files.py
pull_scp/log.py
pull_scp/pull_scp.py
pull_scp.egg-info/PKG-INFO
pull_scp.egg-info/SOURCES.txt
pull_scp.egg-info/dependency_links.txt
pull_scp.egg-info/entry_points.txt
pull_scp.egg-info/not-zip-safe
pull_scp.egg-info/requires.txt
pull_scp.egg-info/top_level.txt