Metadata-Version: 1.2
Name: pull-scp
Version: 1.2.4
Summary: This plugin application is used to recursively copy data from a remote host into an analysis root node.
Home-page: https://github.com/FNNDSC/pl-pull_scp
Author: Rudolph Pienaar -- FNNDSC
Author-email: rudolph.pienaar@childrens.harvard.edu
License: MIT
Platform: UNKNOWN
Requires-Python: >=3.6
